Metadata-Version: 2.1
Name: beaver-build
Version: 0.1.4
Summary: UNKNOWN
Home-page: UNKNOWN
Author: Till Hoffmann
Author-email: niches_osmosis0a@icloud.com
License: UNKNOWN
Platform: UNKNOWN
Provides-Extra: tests
Provides-Extra: docs
